<?xml version="1.0"?>
<!DOCTYPE hibernate-mapping PUBLIC
        "-//Hibernate/Hibernate Mapping DTD//EN"
        "http://www.hibernate.org/dtd/hibernate-mapping-3.0.dtd">
<hibernate-mapping>
    <class name="model.Programmer"
           table="programmers">
        <id name="id" column="id" type="java.lang.Integer">
            <generator class="increment"/>
        </id>
        <property name="name" column="name" type="text"/>
        <property name="username" column="username" type="text"/>
        <property name="password" column="password" type="text"/>
    </class>
</hibernate-mapping>